README.md
setup.cfg
setup.py
sphinxmix/SphinxClient.py
sphinxmix/SphinxNode.py
sphinxmix/SphinxParams.py
sphinxmix/SphinxParamsC25519.py
sphinxmix/UltrixClient.py
sphinxmix/UltrixNode.py
sphinxmix/__init__.py
sphinxmix.egg-info/PKG-INFO
sphinxmix.egg-info/SOURCES.txt
sphinxmix.egg-info/dependency_links.txt
sphinxmix.egg-info/requires.txt
sphinxmix.egg-info/top_level.txt