Metadata-Version: 1.0
Name: sphinxmix
Version: 0.0.7
Summary: A Python implementation of the Sphinx mix packet format.
Home-page: http://sphinxmix.readthedocs.io/en/latest/
Author: George Danezis
Author-email: g.danezis@ucl.ac.uk
License: 2-clause BSD
Platform: UNKNOWN
